.env
Makefile
docker/.envdocker
docker/Dockerfile
docker/docker-compose.yaml
docker/start_mlflow_server-local.sh
docker/start_mlflow_server.sh
docker/wait-for
docs/assets/Snapperml.png
docs/assets/Snapperml_dark.png
docs/assets/UI.png
docs/assets/banner.png
docs/assets/mlflow.png
docs/assets/snapperml_architecture.png
docs/assets/terminal.png
snapper_ml/__init__.py
snapper_ml/api.py
snapper_ml/data.py
snapper_ml/exceptions.py
snapper_ml/experiments.py
snapper_ml/google_cloud.py
snapper_ml/integrations.py
snapper_ml/loggings.py
snapper_ml/mlflow.py
snapper_ml/utils.py
snapper_ml/UI/README.md
snapper_ml/UI/eslint.config.js
snapper_ml/UI/index.html
snapper_ml/UI/package-lock.json
snapper_ml/UI/package.json
snapper_ml/UI/tsconfig.app.json
snapper_ml/UI/tsconfig.json
snapper_ml/UI/tsconfig.node.json
snapper_ml/UI/vite.config.ts
snapper_ml/UI/public/MLflow-Logo.svg
snapper_ml/UI/public/logo_text.png
snapper_ml/UI/public/logo_white_text.png
snapper_ml/UI/public/snapper.png
snapper_ml/UI/src/App.tsx
snapper_ml/UI/src/main.tsx
snapper_ml/UI/src/vite-env.d.ts
snapper_ml/UI/src/assets/components/About.tsx
snapper_ml/UI/src/assets/components/Contact.tsx
snapper_ml/UI/src/assets/components/Execute.tsx
snapper_ml/UI/src/assets/components/FileUpload.tsx
snapper_ml/UI/src/assets/components/NavBar.tsx
snapper_ml/UI/src/assets/components/Terminal.tsx
snapper_ml/UI/src/assets/components/YamlAttributes.tsx
snapper_ml/UI/src/assets/components/YamlEditor.tsx
snapper_ml/UI/src/styles/about.css
snapper_ml/UI/src/styles/buttons.css
snapper_ml/UI/src/styles/contact.css
snapper_ml/UI/src/styles/dark-mode.css
snapper_ml/UI/src/styles/editor.css
snapper_ml/UI/src/styles/footer.css
snapper_ml/UI/src/styles/global.css
snapper_ml/UI/src/styles/header.css
snapper_ml/UI/src/styles/light-mode.css
snapper_ml/UI/src/styles/navbar.css
snapper_ml/UI/src/styles/terminal.css
snapper_ml/callbacks/__init__.py
snapper_ml/callbacks/core.py
snapper_ml/callbacks/notifiers.py
snapper_ml/config/__init__.py
snapper_ml-0.4.1.dist-info/LICENSE
snapper_ml-0.4.1.dist-info/METADATA
snapper_ml-0.4.1.dist-info/WHEEL
snapper_ml-0.4.1.dist-info/entry_points.txt
snapper_ml-0.4.1.dist-info/top_level.txt
snapper_ml-0.4.1.dist-info/RECORD
