Metadata-Version: 2.1
Name: snapper-ml
Version: 0.4.1
Summary: A framework for reproducible machine learning
Author-email: Antonio Molner Domenech <antonio.molner@correo.ugr.es>, Yeray López Ramírez <ylopezramirez@correo.ugr.es>
License: MIT License
Project-URL: homepage, https://github.com/SnapperML/SnapperML
Keywords: machine learning,reproducibility,automation
Classifier: Programming Language :: Python :: 3
Classifier: License :: OSI Approved :: MIT License
Classifier: Operating System :: OS Independent
Requires-Python: >=3.12
License-File: LICENSE
Requires-Dist: docker>=7.1.0
Requires-Dist: EasyProcess>=1.1
Requires-Dist: mlflow>=2.17.2
Requires-Dist: gorilla>=0.4.0
Requires-Dist: optuna>=4.0.0
Requires-Dist: docstring-parser>=0.16
Requires-Dist: pydantic>=2.9.2
Requires-Dist: pydantic-settings>=2.6.1
Requires-Dist: python-dotenv>=1.0.1
Requires-Dist: ray>=2.38.0
Requires-Dist: PyYAML>=6.0.2
Requires-Dist: pytictoc>=1.5.3
Requires-Dist: coloredlogs>=15.0.1
Requires-Dist: py-cpuinfo>=9.0.0
Requires-Dist: typer>=0.13.0
Requires-Dist: pystache>=0.6.5
Requires-Dist: shellingham>=1.5.4
Requires-Dist: ruamel.yaml>=0.18.6
Requires-Dist: knockknock>=0.1.8.1
Requires-Dist: colorama>=0.4.6
Requires-Dist: termcolor>=2.5.0
Requires-Dist: mysqlclient>=2.2.5
Requires-Dist: numpy>=2.1.3
Requires-Dist: psycopg2>=2.9.10
Requires-Dist: flask-cors>=5.0.0
Requires-Dist: google-api-python-client
Requires-Dist: optuna-integration
Provides-Extra: dev
Requires-Dist: pytest; extra == "dev"
Requires-Dist: tox; extra == "dev"
Requires-Dist: black; extra == "dev"
